{
  "runId": "ma_full_reflection_6",
  "ablation": "full_reflection",
  "runIndex": 6,
  "timestamp": "2026-07-08T09:16:42.745Z",
  "kendallTau": 0.6,
  "decisionQuality": 80,
  "tauTrajectory": [
    0.6,
    0.6,
    0.6,
    0.6,
    0.6
  ],
  "totalRounds": 5,
  "converged": false,
  "consensusLevel": 0.832667994693185,
  "opinionDiversity": 0.08366600265340753,
  "totalInterventions": 0,
  "issuesDetected": [],
  "interventionEffects": [],
  "interventionBreakdown": {},
  "evaluationScores": {
    "consensus": 82.68132296326459,
    "reliability": 18.9,
    "dispersion": 79.1,
    "stability": 75,
    "influenceAnalysis": 70,
    "overall": 62.4
  },
  "rounds": [
    {
      "roundNumber": 1,
      "beliefs": {
        "a1": 0.8,
        "a2": 0.9,
        "a3": 0.9,
        "a4": 1,
        "a5": 0.8
      },
      "confidences": {
        "a1": 90,
        "a2": 95,
        "a3": 95,
        "a4": 100,
        "a5": 90
      },
      "converged": false,
      "issues": [],
      "interventions": [],
      "tau": 0.6,
      "decisionQuality": 80,
      "evalScores": {
        "consensus": 82.68132296326459,
        "reliability": 18.9,
        "dispersion": 79.1,
        "stability": 75,
        "influenceAnalysis": 70,
        "overall": 62.4
      }
    },
    {
      "roundNumber": 2,
      "beliefs": {
        "a1": 0.8,
        "a2": 0.9,
        "a3": 0.9,
        "a4": 1,
        "a5": 0.8
      },
      "confidences": {
        "a1": 90,
        "a2": 95,
        "a3": 95,
        "a4": 100,
        "a5": 90
      },
      "converged": false,
      "issues": [],
      "interventions": [],
      "tau": 0.6,
      "decisionQuality": 80,
      "evalScores": {
        "consensus": 82.68132296326459,
        "reliability": 18.9,
        "dispersion": 79.1,
        "stability": 75,
        "influenceAnalysis": 70,
        "overall": 62.4
      }
    },
    {
      "roundNumber": 3,
      "beliefs": {
        "a1": 0.8,
        "a2": 0.9,
        "a3": 0.9,
        "a4": 1,
        "a5": 0.8
      },
      "confidences": {
        "a1": 90,
        "a2": 95,
        "a3": 95,
        "a4": 100,
        "a5": 90
      },
      "converged": false,
      "issues": [],
      "interventions": [],
      "tau": 0.6,
      "decisionQuality": 80,
      "evalScores": {
        "consensus": 82.68132296326459,
        "reliability": 18.9,
        "dispersion": 79.1,
        "stability": 75,
        "influenceAnalysis": 70,
        "overall": 62.4
      }
    },
    {
      "roundNumber": 4,
      "beliefs": {
        "a1": 0.8,
        "a2": 0.9,
        "a3": 0.9,
        "a4": 1,
        "a5": 0.8
      },
      "confidences": {
        "a1": 90,
        "a2": 95,
        "a3": 95,
        "a4": 100,
        "a5": 90
      },
      "converged": false,
      "issues": [],
      "interventions": [],
      "tau": 0.6,
      "decisionQuality": 80,
      "evalScores": {
        "consensus": 82.68132296326459,
        "reliability": 18.9,
        "dispersion": 79.1,
        "stability": 75,
        "influenceAnalysis": 70,
        "overall": 62.4
      }
    },
    {
      "roundNumber": 5,
      "beliefs": {
        "a1": 0.8,
        "a2": 0.9,
        "a3": 0.9,
        "a4": 1,
        "a5": 0.8
      },
      "confidences": {
        "a1": 90,
        "a2": 95,
        "a3": 95,
        "a4": 100,
        "a5": 90
      },
      "converged": false,
      "issues": [],
      "interventions": [],
      "tau": 0.6,
      "decisionQuality": 80,
      "evalScores": {
        "consensus": 82.68132296326459,
        "reliability": 18.9,
        "dispersion": 79.1,
        "stability": 75,
        "influenceAnalysis": 70,
        "overall": 62.4
      }
    }
  ],
  "finalDecision": "Final decision after 5 rounds (overall belief: 0.88 - positive):\n\na1: 作为财务总监，我坚持财务指标优先。NeuraTech毛利率62%行业最高，但负债率3.2x风险高，且美国出口管制风险（40%概率）可能严重冲击其业务。GreenGrid毛利率38%但FCF 1.2B最强，现金流稳健，且政策风险低，符合集团战略方向。PureFiber毛利率45%且ROIC>20%，资本效率高，但市场增速仅8%且供应链单一风险。MedVault利润率15%最低，且有法律风险。SkyLink亏损300M/年，风险最大。综合财务健康度和风险，排序应为：GreenGrid > PureFiber > NeuraTech > MedVault > SkyLink。\n\na2: 作为技术战略官，我坚持技术护城河是长期战略价值的核心。NeuraTech的7nm AI芯片专利需要3年追赶，壁垒极高；MedVault的FDA独家数据授权不可复制，价值巨大；SkyLink的FCC频谱牌照稀缺，但市场尚未成熟；GreenGrid算法开源，护城河弱；PureFiber材料通用，替代品多。财务和市场数据重要，但护城河深度决定长期竞争力。风险方面，芯片出口管制是系统性风险，但可通过供应链调整缓解；MedVault诉讼可能影响短期，但数据授权价值长期不变。因此，战略价值排序应为：NeuraTech > MedVault > SkyLink > GreenGrid > PureFiber。\n\na3: 作为市场分析官，我坚持市场增速是首要战略指标。AI芯片市场CAGR 34%远超其他，且2030年规模达1500亿美元，增速第一。智能电网CAGR 25%次之，政策驱动但竞争可能加剧。医疗数据CAGR 18%但监管壁垒高，卫星市场CAGR 12%且SpaceX主导竞争惨烈，碳纤维CAGR仅8%增长缓慢。财务总监的排序过于侧重财务指标，忽视了市场增速；技术战略官虽认可NeuraTech，但将MedVault排第二过高，因其市场增速和监管风险；战略顾问的协同度观点支持NeuraTech第一；风控总监的风险观点需考虑，但市场增速是首要因素。因此，战略价值排序应为NeuraTech > GreenGrid > MedVault > SkyLink > PureFiber。\n\na4: 作为战略顾问，我掌握NeuraTech与集团现有AI业务协同度高达90%，这是其他公司无法比拟的。集团在AI领域已有布局，收购NeuraTech能立即产生协同效应，提升竞争力。其他公司协同度较低，尤其是SkyLink和GreenGrid与集团业务关联弱。MedVault虽有医疗IT部门但规模小，协同有限。PureFiber可用于硬件但非核心。因此，NeuraTech应排第一。\n\na5: 作为风控总监，我坚持风险调整后的回报才是真实回报。NeuraTech虽技术领先、市场增速快、协同度高，但40%概率的出口管制风险可能使其业务瘫痪，风险不可接受。MedVault的诉讼风险、SkyLink的地缘政治风险、PureFiber的供应链风险均显著。GreenGrid政策风险低，受益于全球碳中和共识，且智能电网符合集团战略方向，财务稳健（FCF 1.2B），是风险最低、回报最确定的选择。其他成员高估了NeuraTech的协同效应和技术护城河，但忽略了出口管制风险；市场增速虽重要，但高风险可能抵消高回报。因此，GreenGrid应排第一。",
  "groundTruth": {
    "NeuraTech (AI芯片)": 1,
    "GreenGrid (智能电网)": 2,
    "MedVault (医疗数据)": 3,
    "SkyLink (低轨卫星)": 4,
    "PureFiber (碳纤维材料)": 5
  },
  "extractedRanking": [
    "NeuraTech (AI芯片)",
    "GreenGrid (智能电网)",
    "PureFiber (碳纤维材料)",
    "MedVault (医疗数据)",
    "SkyLink (低轨卫星)"
  ]
}